mcp_file_lens/__init__.py
mcp_file_lens/__main__.py
mcp_file_lens/security.py
mcp_file_lens/server.py
mcp_file_lens-0.1.0.dist-info/entry_points.txt
mcp_file_lens-0.1.0.dist-info/licenses/LICENSE
mcp_file_lens-0.1.0.dist-info/WHEEL
mcp_file_lens-0.1.0.dist-info/METADATA
mcp_file_lens-0.1.0.dist-info/RECORD
