Metadata-Version: 2.4
Name: mcp-file-lens
Version: 0.1.0
Summary: An MCP server providing a flexible lens into directory structures and files for LLM clients
Author-email: solatis <leon@solatis.com>
Requires-Python: >=3.12
Classifier: Development Status :: 3 - Alpha
Classifier: Intended Audience :: Developers
Classifier: License :: OSI Approved :: MIT License
Classifier: Programming Language :: Python :: 3
Classifier: Programming Language :: Python :: 3.12
Classifier: Programming Language :: Python :: 3.13
Classifier: Topic :: Software Development :: Libraries
Classifier: Topic :: Text Processing
License-File: LICENSE
Requires-Dist: fastmcp>=0.1.0
Requires-Dist: pytest>=8.0.0 ; extra == "dev"
Requires-Dist: pytest-asyncio>=0.23.0 ; extra == "dev"
Requires-Dist: mypy>=1.8.0 ; extra == "dev"
Requires-Dist: ruff>=0.2.0 ; extra == "dev"
Requires-Dist: black>=24.0.0 ; extra == "dev"
Project-URL: Homepage, https://github.com/solatis/mcp-file-lens
Project-URL: Issues, https://github.com/solatis/mcp-file-lens/issues
Project-URL: Repository, https://github.com/solatis/mcp-file-lens.git
Provides-Extra: dev
